{"taxon":{"genus":"Parachtes","author":"Alicata, 1964","taxonRank":"genus","status":"VALID","family":"Dysderidae","familyObject":{"family":"Dysderidae","author":"C. L. Koch, 1837","famLsid":"urn:lsid:nmbe.ch:spiderfam:0071"},"lsid":"urn:lsid:nmbe.ch:spidergen:00493","referenceObject":{"reference":"Alicata, P. (1964b). Le specie italiane di <i>Harpactocrates<\/i> e di <i>Parachtes<\/i> n. gen. (Araneae, Dysderidae). <i>Annuario dell'Istituto e Museo di Zoologia dell'Universita di Napoli<\/i> <b>16<\/b>(3): 1-40.","doi":null,"pageDescription":null}}}