{"taxon":{"genus":"Goleba","author":"Wanless, 1980","taxonRank":"genus","status":"VALID","family":"Salticidae","familyObject":{"family":"Salticidae","author":"Blackwall, 1841","famLsid":"urn:lsid:nmbe.ch:spiderfam:0101"},"lsid":"urn:lsid:nmbe.ch:spidergen:02968","referenceObject":{"reference":"Wanless, F. R. (1980d). A revision of the spider genera <i>Asemonea<\/i> and <i>Pandisus<\/i> (Araneae: Salticidae). <i>Bulletin of the British Museum of Natural History<\/i> (Zool.) <b>39<\/b>(4): 213-257.","doi":"","pageDescription":null}}}