{"taxon":{"genus":"Microstigmata","author":"Strand, 1932","taxonRank":"genus","status":"VALID","family":"Microstigmatidae","familyObject":{"family":"Microstigmatidae","author":"Roewer, 1942","famLsid":"urn:lsid:nmbe.ch:spiderfam:0008"},"lsid":"urn:lsid:nmbe.ch:spidergen:00143","referenceObject":{"reference":"Strand, E. (1932). Miscellanea nomenclatorica zoologica et palaeontologica, III, IV. <i>Folia Zoologica et Hydrobiologica, Rig\u0101<\/i> <b>4<\/b>: 133-147, 193-196.","doi":"","pageDescription":null}}}