{"taxon":{"genus":"Hinewaia","author":"\u017babka & Pollard, 2002","taxonRank":"genus","status":"VALID","family":"Salticidae","familyObject":{"family":"Salticidae","author":"Blackwall, 1841","famLsid":"urn:lsid:nmbe.ch:spiderfam:0101"},"lsid":"urn:lsid:nmbe.ch:spidergen:03584","referenceObject":{"reference":"\u017babka, M. &amp; Pollard, S. D. (2002a). <i>Hinewaia<\/i>, a new genus of Salticidae (Arachnida: Araneae) from New Zealand. <i>Annales Zoologici, Warszawa<\/i> <b>52<\/b>: 597-600.","doi":null,"pageDescription":null}}}