{"taxon":{"genus":"Mburuvicha","author":"Scioscia, 1993","taxonRank":"genus","status":"VALID","family":"Salticidae","familyObject":{"family":"Salticidae","author":"Blackwall, 1841","famLsid":"urn:lsid:nmbe.ch:spiderfam:0101"},"lsid":"urn:lsid:nmbe.ch:spidergen:03063","referenceObject":{"reference":"Scioscia, C. L. (1993). Description of <i>Mburuvicha galianoae<\/i>, new genus and species (Araneae, Salticidae). <i>Bulletin of the British Arachnological Society<\/i> <b>9<\/b>: 123-125.","doi":null,"pageDescription":null}}}