{"taxon":{"species":"ricketti","subspecies":null,"author":"(Pocock, 1901)","taxonRank":"species","status":"VALID","genus":"Cyclocosmia","genusObject":{"genus":"Cyclocosmia","author":"Ausserer, 1871","genLsid":"urn:lsid:nmbe.ch:spidergen:00066"},"family":"Halonoproctidae","familyObject":{"family":"Halonoproctidae","author":"Pocock, 1901","famLsid":"urn:lsid:nmbe.ch:spiderfam:0130"},"distribution":"China","lsid":"urn:lsid:nmbe.ch:spidersp:000539","referenceObject":{"reference":"Pocock, R. I. (1901e). On some new trap-door spiders from China. <i>Proceedings of the Zoological Society of London<\/i> <b>70<\/b>(2): 207-215, pl. 21. doi: <a href=\"https:\/\/doi.org\/10.1111\/j.1469-7998.1901.tb08540.x\" target=\"_blank\">10.1111\/j.1469-7998.1901.tb08540.x<\/a>","doi":"10.1111\/j.1469-7998.1901.tb08540.x","pageDescription":null}}}