{"taxon":{"species":"submissum","subspecies":null,"author":"Gertsch & Davis, ","taxonRank":"species","status":"VALID","genus":"Theridion","genusObject":{"genus":"Theridion","author":"Walckenaer, 1805","genLsid":"urn:lsid:nmbe.ch:spidergen:00725"},"family":"Theridiidae","familyObject":{"family":"Theridiidae","author":"Sundevall, 1833","famLsid":"urn:lsid:nmbe.ch:spiderfam:0099"},"distribution":"USA, Mexico, Bahama Is., Jamaica","lsid":"urn:lsid:nmbe.ch:spidersp:008710","referenceObject":{"reference":"Gertsch, W. J. &amp; Davis, L. I. (1936). New spiders from Texas. <i>American Museum Novitates<\/i> <b>881<\/b>: 1-21.","doi":null,"pageDescription":null}}}