{"taxon":{"species":"fuscipalpis","subspecies":null,"author":"(Denis, 1962)","taxonRank":"species","status":"VALID","genus":"Micrargus","genusObject":{"genus":"Micrargus","author":"Dahl, 1886","genLsid":"urn:lsid:nmbe.ch:spidergen:01095"},"family":"Linyphiidae","familyObject":{"family":"Linyphiidae","author":"Blackwall, 1859","famLsid":"urn:lsid:nmbe.ch:spiderfam:0103"},"distribution":"Uganda","lsid":"urn:lsid:nmbe.ch:spidersp:010267","referenceObject":{"reference":"Denis, J. (1962g). Notes sur les \u00e9rigonides. XX. Erigonides d'Afrique orientale avec quelques remarques sur les erigonides \u00e9thiopiens. <i>Revue de Zoologie et de Botanique Africaines<\/i> <b>65<\/b>: 169-203.","doi":null,"pageDescription":null}}}