{"taxon":{"species":"latithorax","subspecies":null,"author":"Strand, ","taxonRank":"species","status":"VALID","genus":"Tarsiphantes","genusObject":{"genus":"Tarsiphantes","author":"Strand, 1905","genLsid":"urn:lsid:nmbe.ch:spidergen:03685"},"family":"Linyphiidae","familyObject":{"family":"Linyphiidae","author":"Blackwall, 1859","famLsid":"urn:lsid:nmbe.ch:spiderfam:0103"},"distribution":"Russia (Europe to Far North East), Alaska, Canada, Greenland","lsid":"urn:lsid:nmbe.ch:spidersp:013187","referenceObject":{"reference":"Strand, E. (1905). Araneae. In: Report of the Second Norwegian Arctic Expedition in the 'Fram'. Kristiania 3, 22-30.","doi":null,"pageDescription":null}}}