{"taxon":{"species":"onoi","subspecies":null,"author":"Tanikawa, ","taxonRank":"species","status":"VALID","genus":"Larinia","genusObject":{"genus":"Larinia","author":"Simon, 1874","genLsid":"urn:lsid:nmbe.ch:spidergen:01501"},"family":"Araneidae","familyObject":{"family":"Araneidae","author":"Clerck, 1757","famLsid":"urn:lsid:nmbe.ch:spiderfam:0102"},"distribution":"Japan","lsid":"urn:lsid:nmbe.ch:spidersp:016272","referenceObject":{"reference":"Tanikawa, A. (1989). Japanese spiders of the genus <i>Larinia<\/i> Simon (Araneae: Araneidae). <i>Acta Arachnologica<\/i> <b>38<\/b>(2): 31-47. doi: <a href=\"https:\/\/doi.org\/10.2476\/asjaa.38.31\" target=\"_blank\">10.2476\/asjaa.38.31<\/a>","doi":"10.2476\/asjaa.38.31","pageDescription":null}}}