{"taxon":{"species":"canacus","subspecies":null,"author":"Berland, ","taxonRank":"species","status":"VALID","genus":"Araneus","genusObject":{"genus":"Araneus","author":"Clerck, 1757","genLsid":"urn:lsid:nmbe.ch:spidergen:01440"},"family":"Araneidae","familyObject":{"family":"Araneidae","author":"Clerck, 1757","famLsid":"urn:lsid:nmbe.ch:spiderfam:0102"},"distribution":"New Caledonia","lsid":"urn:lsid:nmbe.ch:spidersp:014771","referenceObject":{"reference":"Berland, L. (1931b). Sur quelques araign\u00e9es envoy\u00e9es de Nouvelle Cal\u00e9donie par M. Risbec. <i>Bulletin du Mus\u00e9um National d'Histoire Naturelle de Paris<\/i> (2) <b>3<\/b>: 666-672.","doi":null,"pageDescription":null}}}