{"taxon":{"species":"altimontanus","subspecies":null,"author":"Deltshev, ","taxonRank":"species","status":"VALID","genus":"Diplocephalus","genusObject":{"genus":"Diplocephalus","author":"Bertkau, 1883","genLsid":"urn:lsid:nmbe.ch:spidergen:00931"},"family":"Linyphiidae","familyObject":{"family":"Linyphiidae","author":"Blackwall, 1859","famLsid":"urn:lsid:nmbe.ch:spiderfam:0103"},"distribution":"Bulgaria","lsid":"urn:lsid:nmbe.ch:spidersp:010041","referenceObject":{"reference":"Deltshev, C. D. (1984). A new <i>Diplocephalus<\/i> species from the Bulgarian mountains (Arachnida, Araneae, Erigonidae). <i>Reichenbachia<\/i> <b>22<\/b>: 91-93.","doi":null,"pageDescription":null}}}