{"taxon":{"species":"luteolum","subspecies":null,"author":"(Loksa, 1965)","taxonRank":"species","status":"VALID","genus":"Nenilinium","genusObject":{"genus":"Nenilinium","author":"Eskov, 1988","genLsid":"urn:lsid:nmbe.ch:spidergen:01128"},"family":"Linyphiidae","familyObject":{"family":"Linyphiidae","author":"Blackwall, 1859","famLsid":"urn:lsid:nmbe.ch:spiderfam:0103"},"distribution":"Russia (Far East), Mongolia","lsid":"urn:lsid:nmbe.ch:spidersp:010689","referenceObject":{"reference":"Loksa, I. (1965). Araneae. Ergebnisse der zoologischen Forschungen von Dr. Z. Kaszab in der Mongolei. <i>Reichenbachia<\/i> <b>7<\/b>: 1-32.","doi":"","pageDescription":null}}}