{"taxon":{"species":"kirghizica","subspecies":null,"author":"Tanasevitch, ","taxonRank":"species","status":"VALID","genus":"Minicia","genusObject":{"genus":"Minicia","author":"Thorell, 1875","genLsid":"urn:lsid:nmbe.ch:spidergen:01109"},"family":"Linyphiidae","familyObject":{"family":"Linyphiidae","author":"Blackwall, 1859","famLsid":"urn:lsid:nmbe.ch:spiderfam:0103"},"distribution":"Central Asia","lsid":"urn:lsid:nmbe.ch:spidersp:011862","referenceObject":{"reference":"Tanasevitch, A. V. (1985b). New species of spiders of the family Linyphiidae (Aranei) from Kirghizia. <i>Entomologicheskoe Obozrenie<\/i> <b>64<\/b>: 845-854.","doi":null,"pageDescription":null}}}