{"taxon":{"species":"alpica","subspecies":null,"author":"Thaler, ","taxonRank":"species","status":"VALID","genus":"Pelecopsis","genusObject":{"genus":"Pelecopsis","author":"Simon, 1864","genLsid":"urn:lsid:nmbe.ch:spidergen:01189"},"family":"Linyphiidae","familyObject":{"family":"Linyphiidae","author":"Blackwall, 1859","famLsid":"urn:lsid:nmbe.ch:spiderfam:0103"},"distribution":"Alps (Switzerland, Austria, Italy)","lsid":"urn:lsid:nmbe.ch:spidersp:012238","referenceObject":{"reference":"Thaler, K. (1991a). \u00dcber wenig bekannte Zwergspinnen aus den Alpen \u2013 VIII (Arachnida: Aranei, Linyphiidae: Erigoninae). <i>Revue Suisse de Zoologie<\/i> <b>98<\/b>(1): 165-184. doi: <a href=\"https:\/\/doi.org\/10.5962\/bhl.part.79783\" target=\"_blank\">10.5962\/bhl.part.79783<\/a>","doi":"10.5962\/bhl.part.79783","pageDescription":null}}}