{"taxon":{"species":"vatovae","subspecies":null,"author":"Caporiacco, ","taxonRank":"species","status":"VALID","genus":"Dolomedes","genusObject":{"genus":"Dolomedes","author":"Latreille, 1804","genLsid":"urn:lsid:nmbe.ch:spidergen:01707"},"family":"Dolomedidae","familyObject":{"family":"Dolomedidae","author":"Simon, 1876","famLsid":"urn:lsid:nmbe.ch:spiderfam:0161"},"distribution":"Ethiopia","lsid":"urn:lsid:nmbe.ch:spidersp:019671","referenceObject":{"reference":"Caporiacco, L. di (1940c). Aracnidi raccolte nella Reg. dei Laghi Etiopici della Fossa Galla. <i>Atti della Reale Accademia d'Italia<\/i> <b>11<\/b>: 767-873.","doi":null,"pageDescription":null}}}