{"taxon":{"species":"mulcetus","subspecies":null,"author":"Chickering, ","taxonRank":"species","status":"VALID","genus":"Trachelas","genusObject":{"genus":"Trachelas","author":"L. Koch, 1872","genLsid":"urn:lsid:nmbe.ch:spidergen:02270"},"family":"Trachelidae","familyObject":{"family":"Trachelidae","author":"Simon, 1897","famLsid":"urn:lsid:nmbe.ch:spiderfam:0117"},"distribution":"Jamaica","lsid":"urn:lsid:nmbe.ch:spidersp:025523","referenceObject":{"reference":"Chickering, A. M. (1973a). The spider genus <i>Trachelas<\/i> (Araneae, Clubionidae) in the West Indies. <i>Psyche, Cambridge<\/i> <b>79<\/b>(3, 1972): 215-230. doi: <a href=\"https:\/\/doi.org\/10.1155\/1972\/48060\" target=\"_blank\">10.1155\/1972\/48060<\/a>","doi":"10.1155\/1972\/48060","pageDescription":null}}}