{"taxon":{"species":"alba","subspecies":null,"author":"Simon, ","taxonRank":"species","status":"VALID","genus":"Gephyrina","genusObject":{"genus":"Gephyrina","author":"Simon, 1895","genLsid":"urn:lsid:nmbe.ch:spidergen:02605"},"family":"Philodromidae","familyObject":{"family":"Philodromidae","author":"Thorell, 1869","famLsid":"urn:lsid:nmbe.ch:spiderfam:0057"},"distribution":"Venezuela","lsid":"urn:lsid:nmbe.ch:spidersp:029695","referenceObject":{"reference":"Simon, E. (1895b). Descriptions d'arachnides nouveaux de la famille des Thomisidae. <i>Annales de la Soci\u00e9t\u00e9 Entomologique de Belgique<\/i> <b>39<\/b>: 432-443.","doi":null,"pageDescription":null}}}