{"taxon":{"species":"kempseyi","subspecies":null,"author":"Gray, ","taxonRank":"species","status":"VALID","genus":"Colcarteria","genusObject":{"genus":"Colcarteria","author":"Gray, 1992","genLsid":"urn:lsid:nmbe.ch:spidergen:01858"},"family":"Desidae","familyObject":{"family":"Desidae","author":"Pocock, 1895","famLsid":"urn:lsid:nmbe.ch:spiderfam:0039"},"distribution":"Australia (New South Wales)","lsid":"urn:lsid:nmbe.ch:spidersp:021478","referenceObject":{"reference":"Gray, M. R. (1992b). New desid spiders (Araneae: Desidae) from New Caledonia and eastern Australia. <i>Records of the Australian Museum<\/i> <b>44<\/b>: 253-262.","doi":null,"pageDescription":null}}}