{"taxon":{"species":"ventralis","subspecies":null,"author":"Banks, ","taxonRank":"species","status":"VALID","genus":"Wulfila","genusObject":{"genus":"Wulfila","author":"O. Pickard-Cambridge, 1895","genLsid":"urn:lsid:nmbe.ch:spidergen:02166"},"family":"Anyphaenidae","familyObject":{"family":"Anyphaenidae","author":"Bertkau, 1878","famLsid":"urn:lsid:nmbe.ch:spiderfam:0105"},"distribution":"Bahama Is.","lsid":"urn:lsid:nmbe.ch:spidersp:024128","referenceObject":{"reference":"Banks, N. (1906a). Arachnida from the Bahamas. <i>Bulletin of the American Museum of Natural History<\/i> <b>22<\/b>: 185-189.","doi":null,"pageDescription":null}}}