{"taxon":{"species":"abyssinicus","subspecies":null,"author":"Strand, ","taxonRank":"species","status":"VALID","genus":"Caloctenus","genusObject":{"genus":"Caloctenus","author":"Keyserling, 1877","genLsid":"urn:lsid:nmbe.ch:spidergen:01781"},"family":"Ctenidae","familyObject":{"family":"Ctenidae","author":"Keyserling, 1877","famLsid":"urn:lsid:nmbe.ch:spiderfam:0036"},"distribution":"Ethiopia","lsid":"urn:lsid:nmbe.ch:spidersp:020446","referenceObject":{"reference":"Strand, E. (1917e). Arachnologica varia XXI-XXIV. <i>Archiv f\u00fcr Naturgeschichte<\/i> <b>82<\/b>(A3): 39-44.","doi":null,"pageDescription":null}}}