{"taxon":{"species":"juniperi","subspecies":null,"author":"(Gertsch & Riechert, 1976)","taxonRank":"species","status":"VALID","genus":"Attinella","genusObject":{"genus":"Attinella","author":"Banks, 1905","genLsid":"urn:lsid:nmbe.ch:spidergen:04595"},"family":"Salticidae","familyObject":{"family":"Salticidae","author":"Blackwall, 1841","famLsid":"urn:lsid:nmbe.ch:spiderfam:0101"},"distribution":"USA","lsid":"urn:lsid:nmbe.ch:spidersp:036239","referenceObject":{"reference":"Gertsch, W. J. &amp; Riechert, S. E. (1976). The spatial and temporal partitioning of a desert spider community, with descriptions of new species. <i>American Museum Novitates<\/i> <b>2604<\/b>: 1-25.","doi":null,"pageDescription":null}}}