{"taxon":{"species":"bateae","subspecies":null,"author":"Soares, ","taxonRank":"species","status":"VALID","genus":"Erissus","genusObject":{"genus":"Erissus","author":"Simon, 1895","genLsid":"urn:lsid:nmbe.ch:spidergen:02670"},"family":"Thomisidae","familyObject":{"family":"Thomisidae","author":"Sundevall, 1833","famLsid":"urn:lsid:nmbe.ch:spiderfam:0058"},"distribution":"Brazil","lsid":"urn:lsid:nmbe.ch:spidersp:030385","referenceObject":{"reference":"Soares, B. A. M. (1941). Algumas aranhas novas do Brasil. <i>Pap\u00e9is Avulsos do Departamento de Zoologia, Secretaria de Agricultura, Sao Paolo<\/i> <b>1<\/b>: 255-270.","doi":null,"pageDescription":null}}}