{"taxon":{"species":"kumaonensis","subspecies":"","author":"(Tikader, 1980)","taxonRank":"species","status":"SYNONYM","genus":"Heriaeus","genusObject":{"genus":"Heriaeus","author":"Simon, 1875","genLsid":"urn:lsid:nmbe.ch:spidergen:02680"},"family":"Thomisidae","familyObject":{"family":"Thomisidae","author":"Sundevall, 1833","famLsid":"urn:lsid:nmbe.ch:spiderfam:0058"},"distribution":"India","lsid":"urn:lsid:nmbe.ch:spidersp:030683","referenceObject":{"reference":"","doi":"","pageDescription":""}},"validTaxon":{"_href":"https:\/\/wsc.nmbe.ch\/api\/lsid\/urn:lsid:nmbe.ch:spidersp:030440"}}