{"taxon":{"species":"goianiae","subspecies":null,"author":"Soares & Camargo, ","taxonRank":"species","status":"VALID","genus":"Fluda","genusObject":{"genus":"Fluda","author":"G. W. Peckham & E. G. Peckham, 1892","genLsid":"urn:lsid:nmbe.ch:spidergen:02954"},"family":"Salticidae","familyObject":{"family":"Salticidae","author":"Blackwall, 1841","famLsid":"urn:lsid:nmbe.ch:spiderfam:0101"},"distribution":"Brazil","lsid":"urn:lsid:nmbe.ch:spidersp:033453","referenceObject":{"reference":"Soares, B. A. M. &amp; Camargo, H. F. de A. (1948b). Alguns novos salticidas do Brasil (Araneae, Salticidae). <i>Revista Brasileira de Biologia<\/i> <b>8<\/b>: 421-443.","doi":null,"pageDescription":null}}}