{"taxon":{"species":"esyunini","subspecies":null,"author":"Logunov, ","taxonRank":"species","status":"VALID","genus":"Talavera","genusObject":{"genus":"Talavera","author":"G. W. Peckham & E. G. Peckham, 1909","genLsid":"urn:lsid:nmbe.ch:spidergen:03251"},"family":"Salticidae","familyObject":{"family":"Salticidae","author":"Blackwall, 1841","famLsid":"urn:lsid:nmbe.ch:spiderfam:0101"},"distribution":"Sweden, Finland, Russia (Europe to South Siberia)","lsid":"urn:lsid:nmbe.ch:spidersp:036447","referenceObject":{"reference":"Logunov, D. V. (1992d). Definition of the spider genus <i>Talavera<\/i> (Araneae, Salticidae), with a description of a new species. <i>Bulletin de l'Institut Royal des Sciences Naturelles de Belgique<\/i> (Entomologie) <b>62<\/b>: 75-82.","doi":"","pageDescription":null}}}