{"taxon":{"species":"tricoloripes","subspecies":null,"author":"Strand, ","taxonRank":"species","status":"VALID","genus":"Ozyptila","genusObject":{"genus":"Ozyptila","author":"Simon, 1864","genLsid":"urn:lsid:nmbe.ch:spidergen:02712"},"family":"Thomisidae","familyObject":{"family":"Thomisidae","author":"Sundevall, 1833","famLsid":"urn:lsid:nmbe.ch:spiderfam:0058"},"distribution":"Turkey, Caucasus, Israel, Iran, Kazakhstan, Turkmenistan","lsid":"urn:lsid:nmbe.ch:spidersp:030913","referenceObject":{"reference":"Strand, E. (1913f). Erste Mitteilung \u00fcber Spinnen aus Pal\u00e4stina, gesammelt von Herrn Dr J. Aharoni. <i>Archiv f\u00fcr Naturgeschichte<\/i> <b>79<\/b>(A10): 147-162.","doi":null,"pageDescription":null}}}