{"taxon":{"species":"ferreus","subspecies":null,"author":"Griswold, ","taxonRank":"species","status":"VALID","genus":"Coccorchestes","genusObject":{"genus":"Coccorchestes","author":"Thorell, 1881","genLsid":"urn:lsid:nmbe.ch:spidergen:02896"},"family":"Salticidae","familyObject":{"family":"Salticidae","author":"Blackwall, 1841","famLsid":"urn:lsid:nmbe.ch:spiderfam:0101"},"distribution":"Australia (Queensland)","lsid":"urn:lsid:nmbe.ch:spidersp:032803","referenceObject":{"reference":"Griswold, C. E. (1984). <i>Coccorchestes<\/i> Thorell newly described from Australia (Araneae: Salticidae). <i>Bulletin of the British Arachnological Society<\/i> <b>6<\/b>: 147-148.","doi":null,"pageDescription":null}}}