{"taxon":{"species":"intricatus","subspecies":null,"author":"Dimitrov & Ribera, ","taxonRank":"species","status":"VALID","genus":"Pholcus","genusObject":{"genus":"Pholcus","author":"Walckenaer, 1805","genLsid":"urn:lsid:nmbe.ch:spidergen:00412"},"family":"Pholcidae","familyObject":{"family":"Pholcidae","author":"C. L. Koch, 1850","famLsid":"urn:lsid:nmbe.ch:spiderfam:0017"},"distribution":"Canary Is.","lsid":"urn:lsid:nmbe.ch:spidersp:039663","referenceObject":{"reference":"Dimitrov, Di. &amp; Ribera, C. (2003). <i>Pholcus intricatus<\/i> (Araneae, Pholcidae), una nueva especie end\u00e9mica de Tenerife (Islas Canarias). <i>Revista Ib\u00e9rica de Aracnolog\u00eda<\/i> <b>8<\/b>: 7-11.","doi":null,"pageDescription":null}}}