{"taxon":{"species":"inyo","subspecies":null,"author":"Slowik, ","taxonRank":"species","status":"VALID","genus":"Psilochorus","genusObject":{"genus":"Psilochorus","author":"Simon, 1893","genLsid":"urn:lsid:nmbe.ch:spidergen:00417"},"family":"Pholcidae","familyObject":{"family":"Pholcidae","author":"C. L. Koch, 1850","famLsid":"urn:lsid:nmbe.ch:spiderfam:0017"},"distribution":"USA","lsid":"urn:lsid:nmbe.ch:spidersp:042486","referenceObject":{"reference":"Slowik, J. (2009). A review of the cellar spider genus <i>Psilochorus<\/i> Simon 1893 in America north of Mexico (Araneae: Pholcidae). <i>Zootaxa<\/i> <b>2144<\/b>: 1-53. doi: <a href=\"https:\/\/doi.org\/10.11646\/zootaxa.2144.1.1\" target=\"_blank\">10.11646\/zootaxa.2144.1.1<\/a>","doi":"10.11646\/zootaxa.2144.1.1","pageDescription":null}}}