{"taxon":{"species":"poncho","subspecies":null,"author":"Brescovit, Rheims & Ott, ","taxonRank":"species","status":"VALID","genus":"Predatoroonops","genusObject":{"genus":"Predatoroonops","author":"Brescovit, Rheims & Ott, 2012","genLsid":"urn:lsid:nmbe.ch:spidergen:04067"},"family":"Oonopidae","familyObject":{"family":"Oonopidae","author":"Simon, 1890","famLsid":"urn:lsid:nmbe.ch:spiderfam:0083"},"distribution":"Brazil","lsid":"urn:lsid:nmbe.ch:spidersp:045069","referenceObject":{"reference":"Brescovit, A. D., Bonaldo, A. B., Santos, A. J., Ott, R. &amp; Rheims, C. A. (2012b). The Brazilian goblin spiders of the new genus <i>Predatoroonops<\/i> (Araneae, Oonopidae). <i>Bulletin of the American Museum of Natural History<\/i> <b>370<\/b>: 1-68. doi: <a href=\"https:\/\/doi.org\/10.1206\/766.1\" target=\"_blank\">10.1206\/766.1<\/a>","doi":"10.1206\/766.1","pageDescription":null}}}