{"taxon":{"species":"fasciaaurinigra","subspecies":null,"author":"Guadanucci & Weinmann, ","taxonRank":"species","status":"VALID","genus":"Neoholothele","genusObject":{"genus":"Neoholothele","author":"Guadanucci & Weinmann, 2015","genLsid":"urn:lsid:nmbe.ch:spidergen:04318"},"family":"Theraphosidae","familyObject":{"family":"Theraphosidae","author":"Thorell, 1869","famLsid":"urn:lsid:nmbe.ch:spiderfam:0010"},"distribution":"Colombia","lsid":"urn:lsid:nmbe.ch:spidersp:048479","referenceObject":{"reference":"Guadanucci, J. P. L. &amp; Weinmann, D. (2015). Description of <i>Neoholothele<\/i> gen. nov. (Araneae, Theraphosidae, Schismatothelinae). <i>Studies on Neotropical Fauna and Environment<\/i> <b>50<\/b>(3): 221-228. doi: <a href=\"https:\/\/doi.org\/10.1080\/01650521.2015.1110309\" target=\"_blank\">10.1080\/01650521.2015.1110309<\/a>","doi":"10.1080\/01650521.2015.1110309","pageDescription":null}}}