{"taxon":{"species":"atlanticus","subspecies":null,"author":"Azevedo, Ott, Griswold & Santos, ","taxonRank":"species","status":"VALID","genus":"Apopyllus","genusObject":{"genus":"Apopyllus","author":"Platnick & Shadab, 1984","genLsid":"urn:lsid:nmbe.ch:spidergen:02397"},"family":"Gnaphosidae","familyObject":{"family":"Gnaphosidae","author":"Banks, 1892","famLsid":"urn:lsid:nmbe.ch:spiderfam:0054"},"distribution":"Brazil","lsid":"urn:lsid:nmbe.ch:spidersp:048806","referenceObject":{"reference":"Azevedo, G. H. F., Ott, R., Griswold, C. E. &amp; Santos, A. J. (2016). A taxonomic revision of the ground spiders of the genus <i>Apopyllus<\/i> (Araneae: Gnaphosidae). <i>Zootaxa<\/i> <b>4178<\/b>(3): 301-327. doi: <a href=\"https:\/\/doi.org\/10.11646\/zootaxa.4178.3.1\" target=\"_blank\">10.11646\/zootaxa.4178.3.1<\/a>","doi":"10.11646\/zootaxa.4178.3.1","pageDescription":null}}}