{"taxon":{"species":"oceanica","subspecies":"","author":"(Walckenaer, 1837)","taxonRank":"species","status":"NOMEN_DUBIUM","genus":"Anyphaena","genusObject":{"genus":"Anyphaena","author":"Sundevall, 1833","genLsid":"urn:lsid:nmbe.ch:spidergen:02118"},"family":"Anyphaenidae","familyObject":{"family":"Anyphaenidae","author":"Bertkau, 1878","famLsid":"urn:lsid:nmbe.ch:spiderfam:0105"},"distribution":"Polynesia","lsid":"urn:lsid:nmbe.ch:spidersp:053989","referenceObject":{"reference":"Walckenaer, C. A. (1837). Histoire naturelle des insectes. Apt\u00e8res. Tome premier. Roret, Paris, 682 pp., pl. 1-15.","doi":"10.5962\/bhl.title.61095","pageDescription":"603"}}}