{"taxon":{"species":"absconditum","subspecies":null,"author":"Ferretti, Nicoletta & Soresi, ","taxonRank":"species","status":"VALID","genus":"Plesiopelma","genusObject":{"genus":"Plesiopelma","author":"Pocock, 1901","genLsid":"urn:lsid:nmbe.ch:spidergen:00267"},"family":"Theraphosidae","familyObject":{"family":"Theraphosidae","author":"Thorell, 1869","famLsid":"urn:lsid:nmbe.ch:spiderfam:0010"},"distribution":"Argentina","lsid":"urn:lsid:nmbe.ch:spidersp:059662","referenceObject":{"reference":"Ferretti, N., Nicoletta, M. &amp; Soresi, D. S. (2024). An integrative taxonomy approach evaluates the limits of the widespread tarantula <i>Plesiopelma longisternale<\/i> (Araneae: Mygalomorphae: Theraphosidae) and reveals a new species from Argentina. <i>Zoologischer Anzeiger<\/i> <b>308<\/b>: 131-143. doi: <a href=\"https:\/\/doi.org\/10.1016\/j.jcz.2023.12.003\" target=\"_blank\">10.1016\/j.jcz.2023.12.003<\/a>","doi":"10.1016\/j.jcz.2023.12.003","pageDescription":null}}}