{"taxon":{"species":"qiong","subspecies":"","author":"Lin \u0026 Li, 2022","taxonRank":"species","status":"VALID","genus":"Boagrius","genusObject":{"genus":"Boagrius","author":"Simon, 1893","genLsid":"urn:lsid:nmbe.ch:spidergen:00608"},"family":"Palpimanidae","familyObject":{"family":"Palpimanidae","author":"Thorell, 1869","famLsid":"urn:lsid:nmbe.ch:spiderfam:0023"},"distribution":"China (Hainan), Japan (Ogasawara Is.)","lsid":"urn:lsid:nmbe.ch:spidersp:054216","referenceObject":{"reference":"Lin, Y. J., Tang, W. Z. \u0026 Li, S. Q. (2022). First record of the genus Boagrius Simon, 1893 from China (Araneae, Palpimanidae). Acta Arachnologica Sinica 31(1): 27-31.","doi":"10.3969\/j.issn.1005-9628.2022.01.004","pageDescription":"28"}}}