{"taxon":{"species":"prabodhi","subspecies":null,"author":"Basumatary, Das, Caleb & Brahma, ","taxonRank":"species","status":"VALID","genus":"Chinattus","genusObject":{"genus":"Chinattus","author":"Logunov, 1999","genLsid":"urn:lsid:nmbe.ch:spidergen:02885"},"family":"Salticidae","familyObject":{"family":"Salticidae","author":"Blackwall, 1841","famLsid":"urn:lsid:nmbe.ch:spiderfam:0101"},"distribution":"India","lsid":"urn:lsid:nmbe.ch:spidersp:052653","referenceObject":{"reference":"Basumatary, P., Das, S., Caleb, J. T. D. &amp; Brahma, D. (2020c). First record of the genus <i>Chinattus<\/i> Logunov 1999 with the description of a new species from India (Araneae: Salticidae: Hasariini). <i>Acta Arachnologica<\/i> <b>69<\/b>(2): 127-129. doi: <a href=\"https:\/\/doi.org\/10.2476\/asjaa.69.127\" target=\"_blank\">10.2476\/asjaa.69.127<\/a>","doi":"10.2476\/asjaa.69.127","pageDescription":null}}}