{"taxon":{"species":"zhengguoi","subspecies":null,"author":"Chu & Li, ","taxonRank":"species","status":"VALID","genus":"Utivarachna","genusObject":{"genus":"Utivarachna","author":"Kishida, 1940","genLsid":"urn:lsid:nmbe.ch:spidergen:02272"},"family":"Trachelidae","familyObject":{"family":"Trachelidae","author":"Simon, 1897","famLsid":"urn:lsid:nmbe.ch:spiderfam:0117"},"distribution":"China","lsid":"urn:lsid:nmbe.ch:spidersp:059247","referenceObject":{"reference":"Chu, C., Li, S. Q., Pham, D. S. &amp; Yao, Z. Y. (2023b). Three new species of the spider genus <i>Utivarachna<\/i> Kishida, 1940 (Araneae, Trachelidae) from China and Vietnam. <i>ZooKeys<\/i> <b>1181<\/b>: 201-217. doi: <a href=\"https:\/\/doi.org\/10.3897\/zookeys.1181.110628\" target=\"_blank\">10.3897\/zookeys.1181.110628<\/a>","doi":"10.3897\/zookeys.1181.110628","pageDescription":null}}}