{"taxon":{"species":"salongensis","subspecies":null,"author":"Pett, ","taxonRank":"species","status":"VALID","genus":"Myrmarachne","genusObject":{"genus":"Myrmarachne","author":"MacLeay, 1839","genLsid":"urn:lsid:nmbe.ch:spidergen:03086"},"family":"Salticidae","familyObject":{"family":"Salticidae","author":"Blackwall, 1841","famLsid":"urn:lsid:nmbe.ch:spiderfam:0101"},"distribution":"DR Congo","lsid":"urn:lsid:nmbe.ch:spidersp:059612","referenceObject":{"reference":"Pett, B. L., Iyomi, D. M. M. &amp; Mbende, M. (2023). Myrmarachnini (Araneae: Salticidae: Salticinae: Astioida) of Salonga National Park, D.R. Congo, with description of a new species and two new species records. <i>Arthropoda Selecta<\/i> <b>32<\/b>(4): 466-473. doi: <a href=\"https:\/\/doi.org\/10.15298\/arthsel.32.4.11\" target=\"_blank\">10.15298\/arthsel.32.4.11<\/a>","doi":"10.15298\/arthsel.32.4.11","pageDescription":null}}}