{"taxon":{"species":"attavirus","subspecies":null,"author":"Chatzaki, ","taxonRank":"species","status":"VALID","genus":"Turkozelotes","genusObject":{"genus":"Turkozelotes","author":"Kovblyuk & Seyyar, 2009","genLsid":"urn:lsid:nmbe.ch:spidergen:03937"},"family":"Gnaphosidae","familyObject":{"family":"Gnaphosidae","author":"Banks, 1892","famLsid":"urn:lsid:nmbe.ch:spiderfam:0054"},"distribution":"Greece (Rhodes), Georgia, Azerba\u0133an","lsid":"urn:lsid:nmbe.ch:spidersp:051328","referenceObject":{"reference":"Chatzaki, M. &amp; Van Keer, J. (2019). Ground spiders (Araneae: Gnaphosidae, Liocranidae, Prodidomidae) from the Greek islands Rodos, Symi and Karpathos, with the description of new species. <i>Zootaxa<\/i> <b>4646<\/b>(3): 434-460. doi: <a href=\"https:\/\/doi.org\/10.11646\/zootaxa.4646.3.2\" target=\"_blank\">10.11646\/zootaxa.4646.3.2<\/a>","doi":"10.11646\/zootaxa.4646.3.2","pageDescription":null}}}