{"taxon":{"species":"setosa","subspecies":"","author":"(Forster, 1964)","taxonRank":"species","status":"HOMONYM_REPLACED","genus":"Mangua","genusObject":{"genus":"Mangua","author":"Forster, 1990","genLsid":"urn:lsid:nmbe.ch:spidergen:00642"},"family":"Physoglenidae","familyObject":{"family":"Physoglenidae","author":"Petrunkevitch, 1928","famLsid":"urn:lsid:nmbe.ch:spiderfam:0122"},"distribution":"New Zealand (Auckland Is., Campbell Is.) ","lsid":"urn:lsid:nmbe.ch:spidersp:056053","referenceObject":{"reference":"","doi":"","pageDescription":""}},"validTaxon":{"_href":"https:\/\/wsc.nmbe.ch\/api\/lsid\/urn:lsid:nmbe.ch:spidersp:006491"}}