{"taxon":{"species":"taynguyen","subspecies":"","author":"Hoang \u0026 Zhang, 2022","taxonRank":"species","status":"VALID","genus":"Pancorius","genusObject":{"genus":"Pancorius","author":"Simon, 1902","genLsid":"urn:lsid:nmbe.ch:spidergen:03119"},"family":"Salticidae","familyObject":{"family":"Salticidae","author":"Blackwall, 1841","famLsid":"urn:lsid:nmbe.ch:spiderfam:0101"},"distribution":"Vietnam","lsid":"urn:lsid:nmbe.ch:spidersp:056964","referenceObject":{"reference":"Hoang, Q. D., Wang, L. Y., Irfan, M., Nguyen, A. D., Tran, T. M. H., Tran, D. M. \u0026 Zhang, Z. S. (2022). Notes on two genera of the jumping spiders, Anarrhotus Simon, 1902 and Pancorius Simon, 1902 (Aranei: Salticidae) in Vietnam, with description of a new species. Arthropoda Selecta 31(4): 477-485.","doi":"10.15298\/arthsel.31.4.08","pageDescription":"481"}}}