{"taxon":{"species":"agelenoides","subspecies":"","author":"B\u00e4ckstam, Drolshagen \u0026 Seiter, 2023","taxonRank":"species","status":"VALID","genus":"Linothele","genusObject":{"genus":"Linothele","author":"Karsch, 1879","genLsid":"urn:lsid:nmbe.ch:spidergen:00038"},"family":"Dipluridae","familyObject":{"family":"Dipluridae","author":"Simon, 1889","famLsid":"urn:lsid:nmbe.ch:spiderfam:0005"},"distribution":"Colombia","lsid":"urn:lsid:nmbe.ch:spidersp:058030","referenceObject":{"reference":"B\u00e4ckstam, C. M., Drolshagen, B. \u0026 Seiter, M. (2023). Linothele agelenoides sp. n., a new species of Linothele Karsch, 1879 (Araneae, Dipluridae) from central Colombia. Annalen des Naturhistorischen Museums in Wien, Serie B 125: 5-12.","doi":"","pageDescription":"3"}}}