{"taxon":{"species":"sciosciae","subspecies":null,"author":"Rubio, Baigorria & Stolar, ","taxonRank":"species","status":"VALID","genus":"Titanattus","genusObject":{"genus":"Titanattus","author":"G. W. Peckham & E. G. Peckham, 1885","genLsid":"urn:lsid:nmbe.ch:spidergen:03276"},"family":"Salticidae","familyObject":{"family":"Salticidae","author":"Blackwall, 1841","famLsid":"urn:lsid:nmbe.ch:spiderfam:0101"},"distribution":"Argentina","lsid":"urn:lsid:nmbe.ch:spidersp:053542","referenceObject":{"reference":"Rubio, G. D., Baigorria, J. E. M. &amp; Stolar, C. E. (2021b). <i>Titanattus<\/i> Peckham &amp; Peckham, 1885 in Argentina (Araneae: Salticidae: Thiodinini), with the description of a new species. <i>Arachnology<\/i> <b>18<\/b>(9): 1070-1076. doi: <a href=\"https:\/\/doi.org\/10.13156\/arac.2021.18.9.1070\" target=\"_blank\">10.13156\/arac.2021.18.9.1070<\/a>","doi":"10.13156\/arac.2021.18.9.1070","pageDescription":null}}}