{"taxon":{"species":"pseudocylindrata","subspecies":null,"author":"Strand, ","taxonRank":"species","status":"SYNONYM","genus":"Lampona","genusObject":{"genus":"Lampona","author":"Thorell, 1869","genLsid":"urn:lsid:nmbe.ch:spidergen:02347"},"family":"Lamponidae","familyObject":{"family":"Lamponidae","author":"Simon, 1893","famLsid":"urn:lsid:nmbe.ch:spiderfam:0076"},"distribution":"Australia (Queensland)","lsid":"urn:lsid:nmbe.ch:spidersp:057774","validTaxon":{"_href":"https:\/\/wsc.nmbe.ch\/api\/lsid\/urn:lsid:nmbe.ch:spidersp:026296"},"referenceObject":{"reference":null,"doi":null,"pageDescription":null}}}