{"taxon":{"species":"ritteri","subspecies":"","author":"(Scopoli, 1763)","taxonRank":"species","status":"NOMEN_DUBIUM","genus":"Heliophanus","genusObject":{"genus":"Heliophanus","author":"C. L. Koch, 1833","genLsid":"urn:lsid:nmbe.ch:spidergen:02983"},"family":"Salticidae","familyObject":{"family":"Salticidae","author":"Blackwall, 1841","famLsid":"urn:lsid:nmbe.ch:spiderfam:0101"},"distribution":"Slovenia","lsid":"urn:lsid:nmbe.ch:spidersp:056199","referenceObject":{"reference":"Scopoli, J. A. (1763). Entomologia carniolica, exhibens insecta carniolae indigena et distributa in ordines, genera, species, varietates. Methodo Linnaeana. Ioannis Thomae Trattner, Vindobonae [= Johannes Thomas Trattner, Wien\/Vienna], 420 pp. (Araneae, pp. 392-404).","doi":"10.5962\/bhl.title.34434","pageDescription":"402"}}}