{"taxon":{"species":"karineae","subspecies":null,"author":"Lecigne, ","taxonRank":"species","status":"VALID","genus":"Sintula","genusObject":{"genus":"Sintula","author":"Simon, 1884","genLsid":"urn:lsid:nmbe.ch:spidergen:01262"},"family":"Linyphiidae","familyObject":{"family":"Linyphiidae","author":"Blackwall, 1859","famLsid":"urn:lsid:nmbe.ch:spiderfam:0103"},"distribution":"Turkey, Israel","lsid":"urn:lsid:nmbe.ch:spidersp:053289","referenceObject":{"reference":"Lecigne, S. (2021a). A new species of <i>Sintula<\/i> (Linyphiidae), redescription of <i>Brigittea innocens<\/i> (Dictynidae) and eight spider species newly recorded for Turkey (Araneae). <i>Arachnologische Mitteilungen<\/i> <b>62<\/b>: 11-34. doi: <a href=\"https:\/\/doi.org\/10.30963\/aramit6204\" target=\"_blank\">10.30963\/aramit6204<\/a>","doi":"10.30963\/aramit6204","pageDescription":null}}}