{"taxon":{"species":"hamata","subspecies":null,"author":"Wang, Framenau & Zhang, ","taxonRank":"species","status":"VALID","genus":"Artoria","genusObject":{"genus":"Artoria","author":"Thorell, 1877","genLsid":"urn:lsid:nmbe.ch:spidergen:01598"},"family":"Lycosidae","familyObject":{"family":"Lycosidae","author":"Sundevall, 1833","famLsid":"urn:lsid:nmbe.ch:spiderfam:0100"},"distribution":"China","lsid":"urn:lsid:nmbe.ch:spidersp:053064","referenceObject":{"reference":"Wang, L. Y., Framenau, V. W. &amp; Zhang, Z. S. (2021). A further study on the wolf spider subfamily Artoriinae from China (Araneae: Lycosidae). <i>Zootaxa<\/i> <b>4964<\/b>(3): 571-584. doi: <a href=\"https:\/\/doi.org\/10.11646\/zootaxa.4964.3.8\" target=\"_blank\">10.11646\/zootaxa.4964.3.8<\/a>","doi":"10.11646\/zootaxa.4964.3.8","pageDescription":null}}}