{"taxon":{"species":"enshiensis","subspecies":"","author":"Hu \u0026 J. Liu, 2024","taxonRank":"species","status":"VALID","genus":"Spinembolia","genusObject":{"genus":"Spinembolia","author":"Saaristo, 2006","genLsid":"urn:lsid:nmbe.ch:spidergen:03647"},"family":"Theridiidae","familyObject":{"family":"Theridiidae","author":"Sundevall, 1833","famLsid":"urn:lsid:nmbe.ch:spiderfam:0099"},"distribution":"China","lsid":"urn:lsid:nmbe.ch:spidersp:063202","referenceObject":{"reference":"Hu, C. H., Liu, C. Y., Chen, K. \u0026 Liu, J. (2024). A new species of the genus Spinembolia Saaristo, 2006 (Araneae: Theridiidae) from China, with two new combinations. Acta Arachnologica Sinica 33(2): 83-88.","doi":"10.3969\/j.issn.1005-9628.2024.02.002","pageDescription":"84"}}}