{"taxon":{"species":"kwenda","subspecies":null,"author":"Otto & Hill, ","taxonRank":"species","status":"VALID","genus":"Maratus","genusObject":{"genus":"Maratus","author":"Karsch, 1878","genLsid":"urn:lsid:nmbe.ch:spidergen:03055"},"family":"Salticidae","familyObject":{"family":"Salticidae","author":"Blackwall, 1841","famLsid":"urn:lsid:nmbe.ch:spiderfam:0101"},"distribution":"Australia (Western Australia)","lsid":"urn:lsid:nmbe.ch:spidersp:066070","referenceObject":{"reference":"Otto, J. C. &amp; Hill, D. E. (2025b). Two new peacock spiders in the <i>Maratus linnaei<\/i> group of southwestern Australia (Araneae: Salticidae: Euophryini: Australphryni). <i>Peckhamia<\/i> <b>341.1<\/b>: 1-77.","doi":"","pageDescription":null}}}