{"taxon":{"species":"birmanicus","subspecies":"","author":"Schwendinger \u0026 Huber, 2024","taxonRank":"species","status":"VALID","genus":"Titanidiops","genusObject":{"genus":"Titanidiops","author":"Simon, 1903","genLsid":"urn:lsid:nmbe.ch:spidergen:00091"},"family":"Idiopidae","familyObject":{"family":"Idiopidae","author":"Simon, 1889","famLsid":"urn:lsid:nmbe.ch:spiderfam:0012"},"distribution":"Myanmar","lsid":"urn:lsid:nmbe.ch:spidersp:063359","referenceObject":{"reference":"Schwendinger, P. J., Huber, S. \u0026 Hongpadharakiree, K. (2024). The genus Titanidiops in South-east Asia (Arachnida: Araneae: Idiopidae). Revue Suisse de Zoologie 131(2): 319-355.","doi":"10.35929\/RSZ.0128","pageDescription":"328"}}}