{"taxon":{"species":"noeun","subspecies":"","author":"J. G. Lee \u0026 J. H. Lee, 2024","taxonRank":"species","status":"VALID","genus":"Pholcus","genusObject":{"genus":"Pholcus","author":"Walckenaer, 1805","genLsid":"urn:lsid:nmbe.ch:spidergen:00412"},"family":"Pholcidae","familyObject":{"family":"Pholcidae","author":"C. L. Koch, 1850","famLsid":"urn:lsid:nmbe.ch:spiderfam:0017"},"distribution":"Korea","lsid":"urn:lsid:nmbe.ch:spidersp:060429","referenceObject":{"reference":"Lee, J. G., Lee, J. H., Choi, D. Y., Park, S. J., Baek, M. J. \u0026 Kim, S. K. (2024a). Nine new species of the genus Pholcus Walckenaer (Araneae: Pholcidae) from South Korea. Zootaxa 5432(2): 179-212.","doi":"10.11646\/zootaxa.5432.2.3","pageDescription":"185"}}}