{"taxon":{"species":"bifidum","subspecies":"","author":"(O. Pickard-Cambridge, 1863)","taxonRank":"species","status":"SYNONYM","genus":"Gonatium","genusObject":{"genus":"Gonatium","author":"Menge, 1868","genLsid":"urn:lsid:nmbe.ch:spidergen:00991"},"family":"Linyphiidae","familyObject":{"family":"Linyphiidae","author":"Blackwall, 1859","famLsid":"urn:lsid:nmbe.ch:spiderfam:0103"},"distribution":"Britain","lsid":"urn:lsid:nmbe.ch:spidersp:060297","referenceObject":{"reference":"","doi":"","pageDescription":""}},"validTaxon":{"_href":"https:\/\/wsc.nmbe.ch\/api\/lsid\/urn:lsid:nmbe.ch:spidersp:010673"}}