{"taxon":{"species":"naja","subspecies":"","author":"Xavier, Brescovit \u0026 Bonaldo, 2025","taxonRank":"species","status":"VALID","genus":"Stethorrhagus","genusObject":{"genus":"Stethorrhagus","author":"Simon, 1896","genLsid":"urn:lsid:nmbe.ch:spidergen:02268"},"family":"Corinnidae","familyObject":{"family":"Corinnidae","author":"Karsch, 1880","famLsid":"urn:lsid:nmbe.ch:spiderfam:0049"},"distribution":"Colombia","lsid":"urn:lsid:nmbe.ch:spidersp:066001","referenceObject":{"reference":"Xavier, C., Brescovit, A. D. \u0026 Bonaldo, A. B. (2025). Revising the revision: on 12 new species of Stethorrhagus Simon, 1896 from Colombia and Ecuador (Araneae: Corinnidae: Corinninae), with reassessments of all previously described species. European Journal of Taxonomy 1013: 1-76.","doi":"10.5852\/ejt.2025.1013.3057","pageDescription":"57"}}}