{"taxon":{"species":"chuchaqui","subspecies":null,"author":"Pe\u00f1aherrera-R., ","taxonRank":"species","status":"VALID","genus":"Chrysometa","genusObject":{"genus":"Chrysometa","author":"Simon, 1894","genLsid":"urn:lsid:nmbe.ch:spidergen:01366"},"family":"Tetragnathidae","familyObject":{"family":"Tetragnathidae","author":"Menge, 1866","famLsid":"urn:lsid:nmbe.ch:spiderfam:0032"},"distribution":"Ecuador","lsid":"urn:lsid:nmbe.ch:spidersp:065234","referenceObject":{"reference":"Pe\u00f1aherrera-R., P. (2025a). On some <i>Chrysometa<\/i> Simon, 1894 species collected from Ecuador: redescription of <i>C. bolivia<\/i>, description of a new species, and comments on the type locality of <i>C. otavalo<\/i> (Araneae, Tetragnathidae). <i>Zootaxa<\/i> <b>5636<\/b>(3): 511-522. doi: <a href=\"https:\/\/doi.org\/10.11646\/zootaxa.5636.3.6\" target=\"_blank\">10.11646\/zootaxa.5636.3.6<\/a>","doi":"10.11646\/zootaxa.5636.3.6","pageDescription":null}}}