{"taxon":{"species":"chimminiensis","subspecies":"","author":"Anju, Asha \u0026 Sudhikumar, 2024","taxonRank":"species","status":"VALID","genus":"Dolichognatha","genusObject":{"genus":"Dolichognatha","author":"O. Pickard-Cambridge, 1869","genLsid":"urn:lsid:nmbe.ch:spidergen:01372"},"family":"Tetragnathidae","familyObject":{"family":"Tetragnathidae","author":"Menge, 1866","famLsid":"urn:lsid:nmbe.ch:spiderfam:0032"},"distribution":"India","lsid":"urn:lsid:nmbe.ch:spidersp:062529","referenceObject":{"reference":"Anju, K. B., Asha, T. J. \u0026 Sudhikumar, A. V. (2024). A new six-eyed species of Dolichognatha O. Pickard Cambridge, 1869 from India (Araneae, Tetragnathidae). Zootaxa 5523(1): 146-150.","doi":"10.11646\/zootaxa.5523.1.10","pageDescription":"146"}}}