{"taxon":{"species":"latapophysis","subspecies":"","author":"(Wunderlich, 2024)","taxonRank":"species","status":"SYNONYM","genus":"Civizelotes","genusObject":{"genus":"Civizelotes","author":"Senglet, 2012","genLsid":"urn:lsid:nmbe.ch:spidergen:04115"},"family":"Gnaphosidae","familyObject":{"family":"Gnaphosidae","author":"Banks, 1892","famLsid":"urn:lsid:nmbe.ch:spiderfam:0054"},"distribution":"Portugal","lsid":"urn:lsid:nmbe.ch:spidersp:062546","referenceObject":{"reference":"","doi":"","pageDescription":""}},"validTaxon":{"_href":"https:\/\/wsc.nmbe.ch\/api\/lsid\/urn:lsid:nmbe.ch:spidersp:046162"}}4ge zur Araneologie 17: 7-51, 102.","doi":"","pageDescription":"30"}}}