{"taxon":{"species":"pacoti","subspecies":"","author":"Brescovit, 2025","taxonRank":"species","status":"VALID","genus":"Cryptachaea","genusObject":{"genus":"Cryptachaea","author":"Archer, 1946","genLsid":"urn:lsid:nmbe.ch:spidergen:04192"},"family":"Theridiidae","familyObject":{"family":"Theridiidae","author":"Sundevall, 1833","famLsid":"urn:lsid:nmbe.ch:spiderfam:0099"},"distribution":"Brazil","lsid":"urn:lsid:nmbe.ch:spidersp:065267","referenceObject":{"reference":"Ara\u00fajo, F. da Silva, Brescovit, A. D., Pereira, L. C., Villanueva-Bonilla, G. A. \u0026 Sobczak, J. F. (2025). Cryptachaea pacoti, a new species of spider from Brazil (Araneae: Theridiidae), with notes on parasitoid-host interaction under the influence of abiotic factors. Zootaxa 5642(3): 271-286.","doi":"10.11646\/zootaxa.5642.3.5","pageDescription":"274"}}}