{"taxon":{"species":"nigripuncta","subspecies":null,"author":"Benjamin & Ranasinghe, ","taxonRank":"species","status":"VALID","genus":"Ebrechtella","genusObject":{"genus":"Ebrechtella","author":"Dahl, 1907","genLsid":"urn:lsid:nmbe.ch:spidergen:02664"},"family":"Thomisidae","familyObject":{"family":"Thomisidae","author":"Sundevall, 1833","famLsid":"urn:lsid:nmbe.ch:spiderfam:0058"},"distribution":"Indonesia (Moluccas)","lsid":"urn:lsid:nmbe.ch:spidersp:064433","referenceObject":{"reference":"Benjamin, S. P. &amp; Ranasinghe, U. G. S. L. (2025). A review of some species of <em>Ebrechtella<\/em> Dahl, 1907 (Araneae: Thomisidae) with description of two new species. <i>ZooNova<\/i> <b>41<\/b>: 1-13. doi: <a href=\"https:\/\/doi.org\/10.5281\/zenodo.15007801\" target=\"_blank\">10.5281\/zenodo.15007801<\/a>","doi":"10.5281\/zenodo.15007801","pageDescription":null}}}