{"taxon":{"species":"paula","subspecies":"","author":"Bola\u00f1o-Manjarres, Benavides \u0026 Osorio, 2024","taxonRank":"species","status":"VALID","genus":"Spinosatibiapalpus","genusObject":{"genus":"Spinosatibiapalpus","author":"Gabriel \u0026 Sherwood, 2020","genLsid":"urn:lsid:nmbe.ch:spidergen:04585"},"family":"Theraphosidae","familyObject":{"family":"Theraphosidae","author":"Thorell, 1869","famLsid":"urn:lsid:nmbe.ch:spiderfam:0010"},"distribution":"Colombia","lsid":"urn:lsid:nmbe.ch:spidersp:062837","referenceObject":{"reference":"Bolano-Manjarres, E. D., Benavides-Rivas, L., Tamaris-Turizo, C. E. \u0026 Osorio, L. M. (2024). Two new species of Spinosatibiapalpus Gabriel \u0026amp; Sherwood, 2020 (Araneae: Theraphosidae) from Colombia. Arachnology 19(9): 1205-1210.","doi":"","pageDescription":"1204"}}}