{"taxon":{"species":"pecki","subspecies":null,"author":"(Brignoli, 1980)","taxonRank":"species","status":"VALID","genus":"Telemofila","genusObject":{"genus":"Telemofila","author":"Wunderlich, 1995","genLsid":"urn:lsid:nmbe.ch:spidergen:00354"},"family":"Telemidae","familyObject":{"family":"Telemidae","author":"Fage, 1913","famLsid":"urn:lsid:nmbe.ch:spiderfam:0092"},"distribution":"New Caledonia","lsid":"urn:lsid:nmbe.ch:spidersp:003117","referenceObject":{"reference":"Brignoli, P. M. (1980h). Sur <i>Usofila pecki<\/i> n. sp., araign\u00e9e cavernicole de la Nouvelle-Cal\u00e9donie (Araneae, Telemidae). <i>Revue Suisse de Zoologie<\/i> <b>87<\/b>(2): 605-609. doi: <a href=\"https:\/\/doi.org\/10.5962\/bhl.part.85535\" target=\"_blank\">10.5962\/bhl.part.85535<\/a>","doi":"10.5962\/bhl.part.85535","pageDescription":null}}}