{"taxon":{"species":"tanikawai","subspecies":null,"author":"Irie, ","taxonRank":"species","status":"VALID","genus":"Leptopholcus","genusObject":{"genus":"Leptopholcus","author":"Simon, 1893","genLsid":"urn:lsid:nmbe.ch:spidergen:00394"},"family":"Pholcidae","familyObject":{"family":"Pholcidae","author":"C. L. Koch, 1850","famLsid":"urn:lsid:nmbe.ch:spiderfam:0017"},"distribution":"Japan, China","lsid":"urn:lsid:nmbe.ch:spidersp:003440","referenceObject":{"reference":"Irie, T. (1999a). A new species of the genus <i>Leptopholcus<\/i> (Araneae: Pholcidae) from the Yaeyama Islands, Japan. <i>Acta Arachnologica<\/i> <b>48<\/b>(1): 37-39. doi: <a href=\"https:\/\/doi.org\/10.2476\/asjaa.48.37\" target=\"_blank\">10.2476\/asjaa.48.37<\/a>","doi":"10.2476\/asjaa.48.37","pageDescription":null}}}