{"taxon":{"species":"muralicola","subspecies":null,"author":"Maughan & Fitch, ","taxonRank":"species","status":"VALID","genus":"Pholcus","genusObject":{"genus":"Pholcus","author":"Walckenaer, 1805","genLsid":"urn:lsid:nmbe.ch:spidergen:00412"},"family":"Pholcidae","familyObject":{"family":"Pholcidae","author":"C. L. Koch, 1850","famLsid":"urn:lsid:nmbe.ch:spiderfam:0017"},"distribution":"USA","lsid":"urn:lsid:nmbe.ch:spidersp:003736","referenceObject":{"reference":"Maughan, O. E. &amp; Fitch, H. S. (1976). A new pholcid spider from northeastern Kansas (Arachnida: Araneida). <i>Journal of the Kansas Entomological Society<\/i> <b>49<\/b>: 304-312.","doi":null,"pageDescription":null}}}